vfh/VFH.py
vfh/__init__.py
vfh-0.1.data/scripts/VFH.py
vfh-0.1.data/scripts/__init__.py
vfh-0.1.dist-info/METADATA
vfh-0.1.dist-info/RECORD
vfh-0.1.dist-info/WHEEL
vfh-0.1.dist-info/top_level.txt
