Metadata-Version: 2.1
Name: vfh
Version: 0.1
Summary: A python implementation of VFH pointcloud descriptor.
Home-page: UNKNOWN
Author: Jubaer145
License: MIT
Platform: UNKNOWN
Classifier: Programming Language :: Python :: 3
Classifier: License :: OSI Approved :: MIT License
Classifier: Operating System :: OS Independent
